CHANGES
LICENSE
MANIFEST.in
README.rst
setup.cfg
setup.py
tox.ini
sphinxcontrib/__init__.py
sphinxcontrib/websupport_lean/__init__.py
sphinxcontrib/websupport_lean/builder.py
sphinxcontrib/websupport_lean/core.py
sphinxcontrib/websupport_lean/errors.py
sphinxcontrib/websupport_lean/version.py
sphinxcontrib/websupport_lean/writer.py
sphinxcontrib/websupport_lean/storage/__init__.py
sphinxcontrib/websupport_lean/storage/differ.py
sphinxcontrib/websupport_lean/storage/sqlalchemy_db.py
sphinxcontrib/websupport_lean/storage/sqlalchemystorage.py
sphinxcontrib_websupport_lean.egg-info/PKG-INFO
sphinxcontrib_websupport_lean.egg-info/SOURCES.txt
sphinxcontrib_websupport_lean.egg-info/dependency_links.txt
sphinxcontrib_websupport_lean.egg-info/namespace_packages.txt
sphinxcontrib_websupport_lean.egg-info/not-zip-safe
sphinxcontrib_websupport_lean.egg-info/requires.txt
sphinxcontrib_websupport_lean.egg-info/top_level.txt
tests/path.py
tests/test_websupport.py
tests/util.py
tests/root/Makefile
tests/root/autodoc.txt
tests/root/autodoc_fodder.py
tests/root/autodoc_missing_imports.py
tests/root/bom.po
tests/root/bom.txt
tests/root/conf.py
tests/root/contents.txt
tests/root/ext.py
tests/root/extapi.txt
tests/root/extensions.txt
tests/root/footnote.txt
tests/root/images.txt
tests/root/img.foo.png
tests/root/img.gif
tests/root/img.pdf
tests/root/img.png
tests/root/includes.txt
tests/root/lists.txt
tests/root/literal.inc
tests/root/literal_orig.inc
tests/root/markup.txt
tests/root/math.txt
tests/root/metadata.add
tests/root/objects.txt
tests/root/otherext.foo
tests/root/parsermod.py
tests/root/quotes.inc
tests/root/rimg.png
tests/root/robots.txt
tests/root/subdir.po
tests/root/svgimg.pdf
tests/root/svgimg.svg
tests/root/tabs.inc
tests/root/templated.css_t
tests/root/test.inc
tests/root/wrongenc.inc
tests/root/ziptheme.zip
tests/root/_static/README
tests/root/_static/excluded.css
tests/root/_static/subdir/foo.css
tests/root/_templates/contentssb.html
tests/root/_templates/customsb.html
tests/root/_templates/layout.html
tests/root/en.lproj/localized.txt
tests/root/special/api.h
tests/root/special/code.py
tests/root/subdir/excluded.txt
tests/root/subdir/images.txt
tests/root/subdir/img.png
tests/root/subdir/include.inc
tests/root/subdir/includes.txt
tests/root/subdir/simg.png
tests/root/testtheme/layout.html
tests/root/testtheme/theme.conf
