Metadata-Version: 1.1
Name: sphinxcontrib-websupport-lean
Version: 2.0.0.dev20170818
Summary: Sphinx API for Web Apps
Home-page: https://devel.tech/site/open-source/
Author: Georg Brandl
Author-email: georg@python.org
License: BSD
Download-URL: https://pypi.python.org/pypi/sphinxcontrib-websupport_lean
Platform: any
Classifier: Development Status :: 5 - Production/Stable
Classifier: Environment :: Console
Classifier: Environment :: Web Environment
Classifier: Intended Audience :: Developers
Classifier: Intended Audience :: Education
Classifier: License :: OSI Approved :: BSD License
Classifier: Operating System :: OS Independent
Classifier: Programming Language :: Python
Classifier: Programming Language :: Python :: 2
Classifier: Programming Language :: Python :: 3
Classifier: Framework :: Sphinx
Classifier: Framework :: Sphinx :: Extension
Classifier: Topic :: Documentation
Classifier: Topic :: Documentation :: Sphinx
Classifier: Topic :: Text Processing
Classifier: Topic :: Utilities
